<annotation>
	<folder></folder>
	<filename>DJI_0278_JPG.rf.0c007dda0e22fe72eb8224f23471df4d.jpg</filename>
	<path>DJI_0278_JPG.rf.0c007dda0e22fe72eb8224f23471df4d.jpg</path>
	<source>
		<database>roboflow.ai</database>
	</source>
	<size>
		<width>800</width>
		<height>600</height>
		<depth>3</depth>
	</size>
	<segmented>0</segmented>
	<object>
		<name>dock</name>
		<pose>Unspecified</pose>
		<truncated>0</truncated>
		<difficult>0</difficult>
		<occluded>0</occluded>
		<bndbox>
			<xmin>597</xmin>
			<xmax>800</xmax>
			<ymin>1</ymin>
			<ymax>232</ymax>
		</bndbox>
	</object>
	<object>
		<name>lift</name>
		<pose>Unspecified</pose>
		<truncated>0</truncated>
		<difficult>0</difficult>
		<occluded>0</occluded>
		<bndbox>
			<xmin>609</xmin>
			<xmax>787</xmax>
			<ymin>82</ymin>
			<ymax>267</ymax>
		</bndbox>
	</object>
	<object>
		<name>lift</name>
		<pose>Unspecified</pose>
		<truncated>0</truncated>
		<difficult>0</difficult>
		<occluded>0</occluded>
		<bndbox>
			<xmin>743</xmin>
			<xmax>800</xmax>
			<ymin>1</ymin>
			<ymax>103</ymax>
		</bndbox>
	</object>
</annotation>
